[
  {
    "id": 1,
    "id_filme": 1,
    "nome_usuario": "jhenryson0",
    "nota": "4.8",
    "titulo": "Susan Slept Here",
    "descricao": "dui nec nisi volutpat eleifend donec ut dolor morbi vel lectus in quam fringilla rhoncus mauris enim leo rhoncus sed",
    "data": "16/03/2025"
  },
  {
    "id": 2,
    "id_filme": 2,
    "nome_usuario": "rraith1",
    "nota": "5.8,",
    "titulo": "Asfalttilampaat",
    "descricao": "orci mauris lacinia sapien quis libero nullam sit amet turpis",
    "data": "11/08/2025"
  },
  {
    "id": 3,
    "id_filme": 3,
    "nome_usuario": "aduquesnay2",
    "nota": "7.4",
    ",titulo": "Satyricon",
    "descricao": "non ligula pellentesque ultrices phasellus id sapien in sapien iaculis congue vivamus",
    "data": "17/03/2025"
  },
  {
    "id": 4,
    "id_filme": 4,
    "nome_usuario": "zlackmann3",
    "nota": "2.2",
    "titulo": "Terror in a Texas Town",
    "descricao": "sollicitudin ut suscipit a feugiat et eros vestibulum ac est lacinia nisi venenatis tristique fusce congue diam id ornare imperdiet",
    "data": "14/10/2024"
  },
  {
    "id": 5,
    "id_filme": 5,
    "nome_usuario": "pleblanc4",
    "nota": "2.7",
    ",titulo": "Iron Sky",
    "descricao": "nulla tellus in sagittis dui vel nisl duis ac nibh fusce lacus purus aliquet at feugiat non pretium quis lectus",
    "data": "12/05/2025"
  },
  {
    "id": 6,
    "id_filme": 6,
    "nome_usuario": "djobbins5",
    "nota": "4.5",
    ",titulo": "Pigskin Parade",
    "descricao": "quis tortor id nulla ultrices aliquet maecenas leo odio condimentum id luctus",
    "data": "17/01/2025"
  },
  {
    "id": 7,
    "id_filme": 7,
    "nome_usuario": "tthreadgall6",
    "nota": "3.6",
    ",titulo": "From Above",
    "descricao": "quis libero nullam sit amet turpis elementum ligula vehicula consequat morbi",
    "data": "24/03/2025"
  },
  {
    "id": 8,
    "id_filme": 8,
    "nome_usuario": "bcarman7",
    "nota": "2.9",
    ",titulo": "Stratton Story, The",
    "descricao": "in hac habitasse platea dictumst morbi vestibulum velit id pretium iaculis diam erat",
    "data": "19/02/2025"
  },
  {
    "id": 9,
    "id_filme": 9,
    "nome_usuario": "gluxen8",
    "nota": "6.9",
    ",titulo": "Geronimo: An American Legend",
    "descricao": "lectus pellentesque eget nunc donec quis orci eget orci vehicula condimentum curabitur in",
    "data": "30/04/2025"
  },
  {
    "id": 10,
    "id_filme": 10,
    "nome_usuario": "ospinney9",
    "nota": "6.4",
    ",titulo": "Thomas in Love (Thomas est Amoureux)",
    "descricao": "viverra diam vitae quam suspendisse potenti nullam porttitor lacus at turpis donec posuere metus vitae",
    "data": "06/01/2025"
  }
]